upepper/__init__.py
upepper/cli.py
upepper/exceptions.py
upepper/libpepper.py
upepper/retcode.py
upepper/script.py
upepper-0.1.3.data/scripts/pepper
upepper-0.1.3.dist-info/LICENSE
upepper-0.1.3.dist-info/METADATA
upepper-0.1.3.dist-info/WHEEL
upepper-0.1.3.dist-info/top_level.txt
upepper-0.1.3.dist-info/RECORD
