Metadata-Version: 2.1
Name: upepper
Version: 0.1.3
Summary: A CLI front-end to a running salt-api system
Home-page: http://saltstack.com
Author: Seth House, Phan Dang
Author-email: shouse@saltstack.com, phan.dang@usdatanetworks.com
Classifier: Programming Language :: Python
Classifier: Programming Language :: Cython
Classifier: Programming Language :: Python :: 2.7
Classifier: Programming Language :: Python :: 3.4
Classifier: Programming Language :: Python :: 3.5
Classifier: Programming Language :: Python :: 3.6
Classifier: Development Status :: 5 - Production/Stable
Classifier: Environment :: Console
Classifier: Intended Audience :: Developers
Classifier: Intended Audience :: Information Technology
Classifier: Intended Audience :: System Administrators
Classifier: License :: OSI Approved :: Apache Software License
Classifier: Operating System :: POSIX :: Linux
Classifier: Topic :: System :: Clustering
Classifier: Topic :: System :: Distributed Computing
License-File: LICENSE
Provides-Extra: kerberos
Requires-Dist: requests-gssapi >=1.1.0 ; extra == 'kerberos'
